{
  "timestamp": "2024-10-30T02:24:55.570072-05:00",
  "summary": "### GitHub Notifications Summary\n\n#### Repository: [PrefectHQ/prefect](https://github.com/PrefectHQ/prefect)\n\n1. **Pull Request**: [Patch Selemela07 devcontainer.json](https://github.com/PrefectHQ/prefect/pulls/15860)\n   - **Action**: Review requested\n\n2. **Issue**: [Cannot connect with Pgbouncer when using prefect](https://github.com/PrefectHQ/prefect/issues/14602)\n   - **Status**: Subscribed\n\n3. **Issue**: [Add setting to exclude \"jit\" option from connect_args server_settings](https://github.com/PrefectHQ/prefect/issues/10903)\n   - **Status**: Subscribed\n\nNo urgent items were highlighted in this summary.",
  "events": [
    {
      "type": "PullRequest",
      "timestamp": "2024-10-30T02:24:55.562295-05:00",
      "hash": "13112842182",
      "title": "Patch Selemela07 devcontainer.json",
      "repository": "PrefectHQ/prefect",
      "reason": "review_requested",
      "url": "https://api.github.com/repos/PrefectHQ/prefect/pulls/15860"
    },
    {
      "type": "Issue",
      "timestamp": "2024-10-30T02:24:55.566038-05:00",
      "hash": "11511947642",
      "title": "cannot connect with Pgbouncer when using prefect",
      "repository": "PrefectHQ/prefect",
      "reason": "subscribed",
      "url": "https://api.github.com/repos/PrefectHQ/prefect/issues/14602"
    },
    {
      "type": "Issue",
      "timestamp": "2024-10-30T02:24:55.567149-05:00",
      "hash": "13112919670",
      "title": "Add setting to exclude \"jit\" option from connect_args server_settings",
      "repository": "PrefectHQ/prefect",
      "reason": "subscribed",
      "url": "https://api.github.com/repos/PrefectHQ/prefect/issues/10903"
    }
  ],
  "source_types": [
    "github"
  ],
  "day_id": "2024-10-30"
}
